fabrice/__init__.py
fabrice/__main__.py
fabrice/_version.py
fabrice/config.py
fabrice/connection.py
fabrice/exceptions.py
fabrice/executor.py
fabrice/group.py
fabrice/main.py
fabrice/runners.py
fabrice/tasks.py
fabrice/transfer.py
fabrice/tunnels.py
fabrice/util.py
fabrice/testing/__init__.py
fabrice/testing/base.py
fabrice/testing/fixtures.py
fabrice-1.1.3.dist-info/LICENSE
fabrice-1.1.3.dist-info/METADATA
fabrice-1.1.3.dist-info/WHEEL
fabrice-1.1.3.dist-info/entry_points.txt
fabrice-1.1.3.dist-info/top_level.txt
fabrice-1.1.3.dist-info/RECORD
